netbox_branch_review/__init__.py
netbox_branch_review/choices.py
netbox_branch_review/filtersets.py
netbox_branch_review/forms.py
netbox_branch_review/menu.py
netbox_branch_review/models.py
netbox_branch_review/navigation.py
netbox_branch_review/signals.py
netbox_branch_review/tables.py
netbox_branch_review/urls.py
netbox_branch_review/validators.py
netbox_branch_review/views.py
netbox_branch_review/api/__init__.py
netbox_branch_review/api/serializers.py
netbox_branch_review/api/urls.py
netbox_branch_review/api/views.py
netbox_branch_review/management/__init__.py
netbox_branch_review/management/commands/__init__.py
netbox_branch_review/management/commands/sync_change_review.py
netbox_branch_review/migrations/0001_initial.py
netbox_branch_review/migrations/0002_add_description.py
netbox_branch_review/migrations/0002_repair_ticket_column.py
netbox_branch_review/migrations/0003_merge_0002_add_description_0002_repair_ticket_column.py
netbox_branch_review/migrations/0004_add_comments.py
netbox_branch_review/migrations/0005_make_requested_by_nullable.py
netbox_branch_review/migrations/__init__.py
netbox_branch_review/templates/netbox_branch_review/changerequest.html
netbox_branch_review/templates/netbox_branch_review/changerequest_list.html
netbox_branch_review/templates/netbox_branch_review/includes/changerequest_header.html
netbox_branch_review-0.2.0.dist-info/licenses/LICENSE
netbox_branch_review-0.2.0.dist-info/METADATA
netbox_branch_review-0.2.0.dist-info/WHEEL
netbox_branch_review-0.2.0.dist-info/top_level.txt
netbox_branch_review-0.2.0.dist-info/RECORD
