Metadata-Version: 2.4
Name: netbox-branch-review
Version: 0.2.0
Summary: Branch Review for NetBox
Author: Chris Hale
License-Expression: MIT
Project-URL: Homepage, https://github.com/chale1342/netbox-branch-review
Project-URL: Source, https://github.com/chale1342/netbox-branch-review
Project-URL: Issues, https://github.com/chale1342/netbox-branch-review/issues
Keywords: netbox,plugin,change-management,branch,review,approval
Classifier: Framework :: Django
Classifier: Framework :: Django :: 5
Classifier: Programming Language :: Python :: 3
Classifier: Programming Language :: Python :: 3.10
Classifier: Operating System :: OS Independent
Classifier: Intended Audience :: System Administrators
Classifier: Topic :: System :: Systems Administration
Classifier: Topic :: Internet :: WWW/HTTP
Requires-Python: >=3.10
License-File: LICENSE
Dynamic: license-file
